tradingdate/__init__.py
tradingdate/__version__.py
tradingdate/_typing.py
tradingdate/calendar.py
tradingdate/calendar_engine.py
tradingdate/core.py
tradingdate/date.py
tradingdate-0.0.10.dist-info/LICENSE
tradingdate-0.0.10.dist-info/METADATA
tradingdate-0.0.10.dist-info/WHEEL
tradingdate-0.0.10.dist-info/top_level.txt
tradingdate-0.0.10.dist-info/RECORD
